{
    "id": "2632",
    "title": "Bordado de moda con pedrería crea composiciones y plantillas replicables",
    "url": "https://www.domestika.org/es/courses/2632-bordado-de-moda-con-pedreria-crea-composiciones-y-plantillas-replicables/course",
    "sections": [
        {
            "id": null,
            "title": "Introducción",
            "videos": [
                {
                    "id": null,
                    "title": "Presentación",
                    "m3u8_url": "https://cdn-videos.domestika.org/videos/000/049/325/62b0bff6e3e87bb94c4455b7f0b9ab90/master.m3u8?1676404386"
                },
                {
                    "id": null,
                    "title": "Influencias",
                    "m3u8_url": "https://cdn-videos.domestika.org/videos/000/049/326/4eec486ae2f80086dd6a9bd909fee6b1/master.m3u8?1676404388"
                }
            ],
            "assets": [
                {
                    "name": "content",
                    "url": "https://files.catbox.moe/0dlkew.pdf"
                }
            ]
        },
        {
            "id": null,
            "title": "Desarrollo de un bordado",
            "videos": [
                {
                    "id": null,
                    "title": "Materiales",
                    "m3u8_url": "https://cdn-videos.domestika.org/videos/000/049/327/86eb837a3f66604fd4a1c879dbe42570/master.m3u8?1676404386"
                },
                {
                    "id": null,
                    "title": "Diferentes composiciones",
                    "m3u8_url": "https://cdn-videos.domestika.org/videos/000/049/328/563ba1cc946e9926bdf13a01d1339848/master.m3u8?1676404389"
                },
                {
                    "id": null,
                    "title": "Montar el bastidor",
                    "m3u8_url": "https://cdn-videos.domestika.org/videos/000/049/329/02e3c5eb1a87594c929e36d238591a35/master.m3u8?1676404389"
                }
            ],
            "assets": [
                {
                    "name": "content",
                    "url": "https://files.catbox.moe/tnv895.pdf"
                }
            ]
        },
        {
            "id": null,
            "title": "Tipos de bordado",
            "videos": [
                {
                    "id": null,
                    "title": "Bordado con pedrería lentejuelas",
                    "m3u8_url": "https://cdn-videos.domestika.org/videos/000/049/330/380a138ba46a079b64acabae8e09d949/master.m3u8?1676404399"
                },
                {
                    "id": null,
                    "title": "Bordado con pedrería canutillos",
                    "m3u8_url": "https://cdn-videos.domestika.org/videos/000/049/331/ab1965a1d32d5c6898a60faa3c74d93b/master.m3u8?1676404392"
                },
                {
                    "id": null,
                    "title": "Bordado con pedrería cristales",
                    "m3u8_url": "https://cdn-videos.domestika.org/videos/000/049/332/c1b32f2f6d440abb792dcaabb900f789/master.m3u8?1676404393"
                },
                {
                    "id": null,
                    "title": "Bordado con pedrería mostacillas",
                    "m3u8_url": "https://cdn-videos.domestika.org/videos/000/049/333/3d873f9339e0fa37173f87eaccb599ff/master.m3u8?1676404394"
                },
                {
                    "id": null,
                    "title": "Mezclando materiales",
                    "m3u8_url": "https://cdn-videos.domestika.org/videos/000/049/334/1e4e6da68c42a4de3bbcbc8b2a840410/master.m3u8?1676404399"
                }
            ],
            "assets": [
                {
                    "name": "content",
                    "url": "https://files.catbox.moe/vkewe5.pdf"
                }
            ]
        },
        {
            "id": null,
            "title": "Creación del bordado",
            "videos": [
                {
                    "id": null,
                    "title": "Buscando inspiración y selección de materiales",
                    "m3u8_url": "https://cdn-videos.domestika.org/videos/000/049/335/941ca4515fcfe3eb3fdcbecd8974cc41/master.m3u8?1676404398"
                },
                {
                    "id": null,
                    "title": "Composición",
                    "m3u8_url": "https://cdn-videos.domestika.org/videos/000/049/336/8242f3344dcdd22392fc8a61b796738b/master.m3u8?1676404396"
                },
                {
                    "id": null,
                    "title": "Creación de la plantilla de bordado",
                    "m3u8_url": "https://cdn-videos.domestika.org/videos/000/051/057/a3ec66ba69bbee4a452a892640074eae/master.m3u8?1676405174"
                },
                {
                    "id": null,
                    "title": "Transferencia a tela",
                    "m3u8_url": "https://cdn-videos.domestika.org/videos/000/049/337/11bb618541ae81ca217897874d343f61/master.m3u8?1676404394"
                },
                {
                    "id": null,
                    "title": "Bordado 1",
                    "m3u8_url": "https://cdn-videos.domestika.org/videos/000/049/338/7eb163ce8826b2bbcddde810b2af7145/master.m3u8?1676404400"
                },
                {
                    "id": null,
                    "title": "Bordado 2",
                    "m3u8_url": "https://cdn-videos.domestika.org/videos/000/049/339/d8577c0d7b69e937bf56427d4bf189fb/master.m3u8?1676404405"
                },
                {
                    "id": null,
                    "title": "Bordado 3",
                    "m3u8_url": "https://cdn-videos.domestika.org/videos/000/049/340/08223510eb594a0a0d22218ccac7a752/master.m3u8?1676404405"
                }
            ],
            "assets": [
                {
                    "name": "content",
                    "url": "https://files.catbox.moe/c7mt1q.pdf"
                }
            ]
        },
        {
            "id": null,
            "title": "Detalles finales",
            "videos": [
                {
                    "id": null,
                    "title": "Remate y detalles",
                    "m3u8_url": "https://cdn-videos.domestika.org/videos/000/049/341/b3799e8d41e71728bd71fb1cbf41a0d2/master.m3u8?1676404396"
                },
                {
                    "id": null,
                    "title": "Cuidado de la prenda",
                    "m3u8_url": "https://cdn-videos.domestika.org/videos/000/049/342/d11c2e9bb18c7051deac24ac03a6ef7b/master.m3u8?1676404397"
                }
            ],
            "assets": [
                {
                    "name": "content",
                    "url": "https://files.catbox.moe/jnfsf6.pdf"
                }
            ]
        },
        {
            "id": null,
            "title": "Final Project",
            "videos": [],
            "assets": []
        }
    ],
    "assets": [
        {
            "name": "content",
            "url": "https://files.catbox.moe/gegc28.pdf"
        }
    ],
    "info": {
        "product_id": 2632,
        "product_name": "Textile Embroidery with Beads: Patterns You Can Replicate",
        "teacher_name": "Raquel Ezquerro (Lanusa)",
        "category_id": 12,
        "category_name": "Craft",
        "course_level": "beginner",
        "course_number_of_lessons": 19,
        "course_total_duration_sec": 11197,
        "total_units": 5,
        "subtitles_language": [
            "es",
            "en",
            "pt",
            "de",
            "fr",
            "it",
            "pl",
            "nl",
            "tr"
        ],
        "audio_language": [
            "es"
        ],
        "original_language": "es"
    }
}