{
    "id": "2648",
    "title": "Decoración floral para Cake Design",
    "url": "https://www.domestika.org/es/courses/2648-decoracion-floral-para-cake-design/course",
    "sections": [
        {
            "id": null,
            "title": "Introducción",
            "videos": [
                {
                    "id": null,
                    "title": "Acerca de mí",
                    "m3u8_url": "https://cdn-videos.domestika.org/videos/000/044/203/90ea8663523c8cb23902b89265cec388/master.m3u8?1676401860"
                },
                {
                    "id": null,
                    "title": "Influencias",
                    "m3u8_url": "https://cdn-videos.domestika.org/videos/000/044/204/4113c9d97badd56ea387198416119537/master.m3u8?1676401864"
                }
            ],
            "assets": [
                {
                    "name": "content",
                    "url": "https://files.catbox.moe/gqbo8g.pdf"
                }
            ]
        },
        {
            "id": null,
            "title": "Primeros pasos",
            "videos": [
                {
                    "id": null,
                    "title": "Herramientas y materiales",
                    "m3u8_url": "https://cdn-videos.domestika.org/videos/000/044/205/aea982a0f69e1a2d7ce042bc70672014/master.m3u8?1676401861"
                },
                {
                    "id": null,
                    "title": "Cómo preparar tu pastel para fondant con ganache",
                    "m3u8_url": "https://cdn-videos.domestika.org/videos/000/044/206/f5e9ce1059e04df15181f212f1b3fc3a/master.m3u8?1676401866"
                },
                {
                    "id": null,
                    "title": "Introducción a la pasta de goma los alambres florales y la cinta",
                    "m3u8_url": "https://cdn-videos.domestika.org/videos/000/044/207/63a5a1003c04adf98d3dc016d9c42ab2/master.m3u8?1676401865"
                },
                {
                    "id": null,
                    "title": "Inspiración y bocetos",
                    "m3u8_url": "https://cdn-videos.domestika.org/videos/000/044/208/4c9fa67426fff8bb61f6b7e364a35937/master.m3u8?1676401862"
                },
                {
                    "id": null,
                    "title": "Planificación y mezcla de la paleta de colores",
                    "m3u8_url": "https://cdn-videos.domestika.org/videos/000/044/209/6273afe368dc35a7255930c11b43c977/master.m3u8?1676401867"
                }
            ],
            "assets": [
                {
                    "name": "content",
                    "url": "https://files.catbox.moe/ajlcq8.pdf"
                }
            ]
        },
        {
            "id": null,
            "title": "Creando flores hojas y pastel con textura",
            "videos": [
                {
                    "id": null,
                    "title": "Cómo hacer tus flores 1",
                    "m3u8_url": "https://cdn-videos.domestika.org/videos/000/044/210/344bf946c229c3a66254e2ed1f2c9308/master.m3u8?1676401868"
                },
                {
                    "id": null,
                    "title": "Cómo hacer tus flores 2",
                    "m3u8_url": "https://cdn-videos.domestika.org/videos/000/044/211/cbe4398ba5cdd0b5f4ade851a853c97b/master.m3u8?1676401870"
                },
                {
                    "id": null,
                    "title": "Hojas y ramas",
                    "m3u8_url": "https://cdn-videos.domestika.org/videos/000/044/212/975fd5cc5adade00bc776baaeeeea656/master.m3u8?1676401868"
                },
                {
                    "id": null,
                    "title": "Textura de mármol y envoltura de pasteles 1",
                    "m3u8_url": "https://cdn-videos.domestika.org/videos/000/044/213/c29d4a184f0c3bf21ac08390c8b68c1f/master.m3u8?1676401875"
                },
                {
                    "id": null,
                    "title": "Textura de mármol y envoltura de pasteles 2",
                    "m3u8_url": "https://cdn-videos.domestika.org/videos/000/044/214/4d988b602fea982b0d25a120f00a3598/master.m3u8?1676401864"
                }
            ],
            "assets": [
                {
                    "name": "content",
                    "url": "https://files.catbox.moe/n251ou.pdf"
                }
            ]
        },
        {
            "id": null,
            "title": "Composición final",
            "videos": [
                {
                    "id": null,
                    "title": "Colocación de los elementos de azúcar",
                    "m3u8_url": "https://cdn-videos.domestika.org/videos/000/044/215/925ed83412fe123a4fe675d8c602a4a5/master.m3u8?1676401868"
                },
                {
                    "id": null,
                    "title": "Consejos sobre cómo tomar fotos de tu pastel",
                    "m3u8_url": "https://cdn-videos.domestika.org/videos/000/044/216/cff4c8ab41144eabc348c9493134aa45/master.m3u8?1676401865"
                }
            ],
            "assets": [
                {
                    "name": "content",
                    "url": "https://files.catbox.moe/osiso0.pdf"
                }
            ]
        },
        {
            "id": null,
            "title": "Final Project",
            "videos": [],
            "assets": []
        }
    ],
    "assets": [
        {
            "name": "content",
            "url": "https://files.catbox.moe/9vif2g.pdf"
        }
    ],
    "info": {
        "product_id": 2648,
        "product_name": "Floral Cake Design: Craft Edible Art",
        "teacher_name": "Cynthia Irani",
        "category_id": 21,
        "category_name": "Culinary",
        "course_level": "beginner",
        "course_number_of_lessons": 14,
        "course_total_duration_sec": 8481,
        "total_units": 4,
        "subtitles_language": [
            "en",
            "es",
            "pt",
            "de",
            "fr",
            "it",
            "pl",
            "nl",
            "tr"
        ],
        "audio_language": [
            "en"
        ],
        "original_language": "en"
    }
}