{
    "id": "3707",
    "title": "Diseño de accesorios confecciona tu colección de diademas",
    "url": "https://www.domestika.org/es/courses/3707-diseno-de-accesorios-confecciona-tu-coleccion-de-diademas/course",
    "sections": [
        {
            "id": null,
            "title": "Introducción",
            "videos": [
                {
                    "id": null,
                    "title": "Sobre mí",
                    "m3u8_url": "https://cdn-videos.domestika.org/videos/000/048/934/2ab57e12ef7c9baf9660b5b76895b0af/master.m3u8?1676404212"
                },
                {
                    "id": null,
                    "title": "Inspiración",
                    "m3u8_url": "https://cdn-videos.domestika.org/videos/000/048/935/c7adabe65437cca6b4ee801eee75f40c/master.m3u8?1676404212"
                }
            ],
            "assets": [
                {
                    "name": "content",
                    "url": "https://files.catbox.moe/8i9q8u.pdf"
                }
            ]
        },
        {
            "id": null,
            "title": "Primeros pasos para crear tu colección",
            "videos": [
                {
                    "id": null,
                    "title": "Tendencias y uso",
                    "m3u8_url": "https://cdn-videos.domestika.org/videos/000/048/936/08897e1f69b84a4db87a5af567c56ecd/master.m3u8?1676404215"
                },
                {
                    "id": null,
                    "title": "Tejidos y materiales",
                    "m3u8_url": "https://cdn-videos.domestika.org/videos/000/048/937/61f2662067b91da06556ddc404544655/master.m3u8?1676404215"
                },
                {
                    "id": null,
                    "title": "Referencias y mood board",
                    "m3u8_url": "https://cdn-videos.domestika.org/videos/000/048/938/487f00b50fbe650628b9197da67e985a/master.m3u8?1676404219"
                }
            ],
            "assets": [
                {
                    "name": "content",
                    "url": "https://files.catbox.moe/bjuf9h.pdf"
                }
            ]
        },
        {
            "id": null,
            "title": "Diademas básicas",
            "videos": [
                {
                    "id": null,
                    "title": "Diadema básica plana 1",
                    "m3u8_url": "https://cdn-videos.domestika.org/videos/000/048/940/8edab78b47fc992235ad86afe4c9d193/master.m3u8?1676404221"
                },
                {
                    "id": null,
                    "title": "Diadema básica plana 2",
                    "m3u8_url": "https://cdn-videos.domestika.org/videos/000/048/941/ea3dd61e69916c6f53041f3071baf763/master.m3u8?1676404217"
                },
                {
                    "id": null,
                    "title": "Diadema básica con relieve",
                    "m3u8_url": "https://cdn-videos.domestika.org/videos/000/048/942/db6bc75f3091a19fa7bdeeb6b8987cea/master.m3u8?1676404222"
                }
            ],
            "assets": [
                {
                    "name": "content",
                    "url": "https://files.catbox.moe/cvahke.pdf"
                }
            ]
        },
        {
            "id": null,
            "title": "Diademas moulage y joya",
            "videos": [
                {
                    "id": null,
                    "title": "Introducción y preparación de moulage",
                    "m3u8_url": "https://cdn-videos.domestika.org/videos/000/048/943/d358dd549ff99ac939372fb27296a4cd/master.m3u8?1676404217"
                },
                {
                    "id": null,
                    "title": "Acabados de la diadema moulage 1",
                    "m3u8_url": "https://cdn-videos.domestika.org/videos/000/048/944/002ebba759a64d0f9251c2c8f9d19151/master.m3u8?1676404223"
                },
                {
                    "id": null,
                    "title": "Acabados de la diadema de moulage 2",
                    "m3u8_url": "https://cdn-videos.domestika.org/videos/000/048/945/a4bd27b9345e504101c4dee1c8a6c488/master.m3u8?1676404219"
                },
                {
                    "id": null,
                    "title": "Introducción y acabados de la diadema joya 1",
                    "m3u8_url": "https://cdn-videos.domestika.org/videos/000/048/946/cefb633e811517ee3773462a615e0de8/master.m3u8?1676404226"
                },
                {
                    "id": null,
                    "title": "Introducción y acabados de la diadema joya 2",
                    "m3u8_url": "https://cdn-videos.domestika.org/videos/000/048/947/2e00287f3a4b7aec25c478087cb2f83c/master.m3u8?1676404223"
                }
            ],
            "assets": [
                {
                    "name": "content",
                    "url": "https://files.catbox.moe/1r7wu3.pdf"
                }
            ]
        },
        {
            "id": null,
            "title": "Packaging y redes sociales",
            "videos": [
                {
                    "id": null,
                    "title": "Cómo realizar fotos para tus redes sociales",
                    "m3u8_url": "https://cdn-videos.domestika.org/videos/000/048/949/c82de01d1a27d2c291a08f87a4c2f96b/master.m3u8?1676404216"
                },
                {
                    "id": null,
                    "title": "Packaging y cuidados",
                    "m3u8_url": "https://cdn-videos.domestika.org/videos/000/048/950/04a5cc41b8cd74c17ac4726b1808f394/master.m3u8?1676404217"
                }
            ],
            "assets": [
                {
                    "name": "content",
                    "url": "https://files.catbox.moe/g34jhk.pdf"
                }
            ]
        },
        {
            "id": null,
            "title": "Final Project",
            "videos": [],
            "assets": []
        }
    ],
    "assets": [
        {
            "name": "content",
            "url": "https://files.catbox.moe/c0tgqj.pdf"
        }
    ],
    "info": {
        "product_id": 3707,
        "product_name": "Accessory Design: Create a Headband Collection",
        "teacher_name": "Betto García",
        "category_id": 20,
        "category_name": "Fashion",
        "course_level": "beginner",
        "course_number_of_lessons": 15,
        "course_total_duration_sec": 8319,
        "total_units": 5,
        "subtitles_language": [
            "es",
            "en",
            "pt",
            "de",
            "fr",
            "it",
            "pl",
            "nl",
            "tr"
        ],
        "audio_language": [
            "es",
            "en"
        ],
        "original_language": "es"
    }
}